{"version": 0.6, "generator": "Overpass API 0.7.62.7 375dc00a", "osm3s": {"timestamp_osm_base": "2025-08-07T16:17:06Z", "copyright": "The data included in this document is from www.openstreetmap.org. The data is made available under ODbL."}, "elements": [{"type": "node", "id": 2526280017, "lat": 9.1856188, "lon": 46.6741756}, {"type": "node", "id": 2526280018, "lat": 9.1858303, "lon": 46.6743531}, {"type": "node", "id": 2526280019, "lat": 9.1858777, "lon": 46.6742952}, {"type": "node", "id": 2526280020, "lat": 9.1856662, "lon": 46.6741177}, {"type": "node", "id": 4579789103, "lat": 9.4863831, "lon": 46.866032, "tags": {"amenity": "fuel", "name": "gar adag fuel station"}}, {"type": "node", "id": 8198906646, "lat": 9.4757386, "lon": 46.8708032}, {"type": "node", "id": 8198906647, "lat": 9.4755587, "lon": 46.8707818}, {"type": "node", "id": 8198906648, "lat": 9.4754423, "lon": 46.8704492}, {"type": "node", "id": 8198906649, "lat": 9.4755137, "lon": 46.8700147}, {"type": "node", "id": 8198906650, "lat": 9.4754793, "lon": 46.8694836}, {"type": "node", "id": 8198906651, "lat": 9.4754079, "lon": 46.8689981}, {"type": "node", "id": 8198906652, "lat": 9.4755507, "lon": 46.8689096}, {"type": "node", "id": 8198906653, "lat": 9.4757386, "lon": 46.8690732}, {"type": "node", "id": 8198906654, "lat": 9.4758497, "lon": 46.869505}, {"type": "node", "id": 8198906655, "lat": 9.4758735, "lon": 46.87013}, {"type": "node", "id": 8198906656, "lat": 9.4758761, "lon": 46.8707308}, {"type": "node", "id": 8198966476, "lat": 9.486863, "lon": 46.8942279}, {"type": "node", "id": 8198966477, "lat": 9.4867466, "lon": 46.8942247}, {"type": "node", "id": 8198966478, "lat": 9.4867482, "lon": 46.8941638}, {"type": "node", "id": 8198966479, "lat": 9.4868646, "lon": 46.8941669}, {"type": "node", "id": 8198966480, "lat": 9.4876422, "lon": 46.8939078}, {"type": "node", "id": 8198966481, "lat": 9.4876279, "lon": 46.8940056}, {"type": "node", "id": 8198966482, "lat": 9.4875572, "lon": 46.8939949}, {"type": "node", "id": 8198966483, "lat": 9.4875714, "lon": 46.8938972}, {"type": "node", "id": 8202525869, "lat": 9.4201144, "lon": 46.790152}, {"type": "node", "id": 8202525870, "lat": 9.420032, "lon": 46.7901723}, {"type": "node", "id": 8202525871, "lat": 9.4200476, "lon": 46.7902372}, {"type": "node", "id": 8202525872, "lat": 9.4201299, "lon": 46.7902169}, {"type": "node", "id": 8207407309, "lat": 9.422159, "lon": 46.8136282}, {"type": "node", "id": 8207407310, "lat": 9.4221704, "lon": 46.8136768}, {"type": "node", "id": 8207407311, "lat": 9.4222269, "lon": 46.8136631}, {"type": "node", "id": 8207407312, "lat": 9.4222155, "lon": 46.8136145}, {"type": "node", "id": 8210321660, "lat": 9.3631756, "lon": 46.7030131}, {"type": "node", "id": 8210321661, "lat": 9.3630459, "lon": 46.7030064}, {"type": "node", "id": 8210321662, "lat": 9.3630502, "lon": 46.7029211}, {"type": "node", "id": 8210321663, "lat": 9.3631798, "lon": 46.7029278}, {"type": "node", "id": 8214353954, "lat": 9.5254773, "lon": 46.7155332}, {"type": "node", "id": 8214353955, "lat": 9.525438, "lon": 46.7155324}, {"type": "node", "id": 8214353956, "lat": 9.5254388, "lon": 46.715491}, {"type": "node", "id": 8214353957, "lat": 9.5254782, "lon": 46.7154918}, {"type": "node", "id": 8214353958, "lat": 9.5252072, "lon": 46.7152417}, {"type": "node", "id": 8214353959, "lat": 9.5251663, "lon": 46.7153039}, {"type": "node", "id": 8214353960, "lat": 9.5252061, "lon": 46.7153307}, {"type": "node", "id": 8214353961, "lat": 9.5252469, "lon": 46.7152685}, {"type": "node", "id": 8387503221, "lat": 9.202084, "lon": 46.666521}, {"type": "node", "id": 8387503222, "lat": 9.2020166, "lon": 46.6666329}, {"type": "node", "id": 8387503223, "lat": 9.201965, "lon": 46.666601}, {"type": "node", "id": 8387503224, "lat": 9.2020324, "lon": 46.6664891}, {"type": "node", "id": 8387503229, "lat": 9.2028131, "lon": 46.6676694, "tags": {"amenity": "watering_place", "fixme": "water place?"}}, {"type": "node", "id": 8387503230, "lat": 9.2018464, "lon": 46.6679309, "tags": {"amenity": "watering_place", "fixme": "water place?"}}, {"type": "node", "id": 8387503231, "lat": 9.2023093, "lon": 46.667781, "tags": {"amenity": "watering_place", "fixme": "water place?"}}, {"type": "node", "id": 8894536878, "lat": 9.5493092, "lon": 46.7307092}, {"type": "node", "id": 8894536879, "lat": 9.5493197, "lon": 46.7307029}, {"type": "node", "id": 8894536880, "lat": 9.5493319, "lon": 46.7307041}, {"type": "node", "id": 8894536881, "lat": 9.549341, "lon": 46.7307123}, {"type": "node", "id": 8894536882, "lat": 9.5493388, "lon": 46.7307357}, {"type": "node", "id": 8894536883, "lat": 9.5493283, "lon": 46.730742}, {"type": "node", "id": 8894536884, "lat": 9.5493162, "lon": 46.7307408}, {"type": "node", "id": 8894536885, "lat": 9.549307, "lon": 46.7307326}, {"type": "node", "id": 8894536886, "lat": 9.5493044, "lon": 46.7307206}, {"type": "node", "id": 8894536887, "lat": 9.5493436, "lon": 46.7307244}, {"type": "node", "id": 8894536888, "lat": 9.5492471, "lon": 46.7307982}, {"type": "node", "id": 8894536889, "lat": 9.5492523, "lon": 46.730789}, {"type": "node", "id": 8894536890, "lat": 9.5492618, "lon": 46.7307846}, {"type": "node", "id": 8894536891, "lat": 9.5492721, "lon": 46.7307867}, {"type": "node", "id": 8894536892, "lat": 9.5492803, "lon": 46.7308051}, {"type": "node", "id": 8894536893, "lat": 9.5492751, "lon": 46.7308143}, {"type": "node", "id": 8894536894, "lat": 9.5492656, "lon": 46.7308187}, {"type": "node", "id": 8894536895, "lat": 9.5492553, "lon": 46.7308166}, {"type": "node", "id": 8894536896, "lat": 9.5492483, "lon": 46.7308088}, {"type": "node", "id": 8894536897, "lat": 9.5492791, "lon": 46.7307945}, {"type": "node", "id": 8894537082, "lat": 9.5393301, "lon": 46.7755804}, {"type": "node", "id": 8894537083, "lat": 9.5393334, "lon": 46.7755694}, {"type": "node", "id": 8894537084, "lat": 9.5393425, "lon": 46.7755624}, {"type": "node", "id": 8894537085, "lat": 9.5393539, "lon": 46.7755622}, {"type": "node", "id": 8894537086, "lat": 9.539367, "lon": 46.7755797}, {"type": "node", "id": 8894537087, "lat": 9.5393637, "lon": 46.7755908}, {"type": "node", "id": 8894537088, "lat": 9.5393546, "lon": 46.7755978}, {"type": "node", "id": 8894537089, "lat": 9.5393432, "lon": 46.775598}, {"type": "node", "id": 8894537090, "lat": 9.5393338, "lon": 46.7755914}, {"type": "node", "id": 8894537091, "lat": 9.5393633, "lon": 46.7755688}, {"type": "node", "id": 8894991444, "lat": 9.5317704, "lon": 46.6846914}, {"type": "node", "id": 8894991445, "lat": 9.5317768, "lon": 46.6846805}, {"type": "node", "id": 8894991446, "lat": 9.5317884, "lon": 46.6846755}, {"type": "node", "id": 8894991447, "lat": 9.5318006, "lon": 46.6846784}, {"type": "node", "id": 8894991448, "lat": 9.53181, "lon": 46.6847007}, {"type": "node", "id": 8894991449, "lat": 9.5318035, "lon": 46.6847116}, {"type": "node", "id": 8894991450, "lat": 9.531792, "lon": 46.6847166}, {"type": "node", "id": 8894991451, "lat": 9.5317797, "lon": 46.6847137}, {"type": "node", "id": 8894991452, "lat": 9.5317715, "lon": 46.6847041}, {"type": "node", "id": 8894991453, "lat": 9.5318089, "lon": 46.684688}, {"type": "node", "id": 8894991454, "lat": 9.5317141, "lon": 46.6846788}, {"type": "node", "id": 8894991455, "lat": 9.531721, "lon": 46.68467}, {"type": "node", "id": 8894991456, "lat": 9.531732, "lon": 46.6846687}, {"type": "node", "id": 8894991457, "lat": 9.5317419, "lon": 46.6846868}, {"type": "node", "id": 8894991458, "lat": 9.531735, "lon": 46.6846956}, {"type": "node", "id": 8894991459, "lat": 9.531724, "lon": 46.6846969}, {"type": "node", "id": 8894991460, "lat": 9.5317154, "lon": 46.6846899}, {"type": "node", "id": 8894991461, "lat": 9.5317406, "lon": 46.6846757}, {"type": "node", "id": 8894991462, "lat": 9.5322476, "lon": 46.6877618}, {"type": "node", "id": 8894991463, "lat": 9.5322552, "lon": 46.6877548}, {"type": "node", "id": 8894991464, "lat": 9.5322653, "lon": 46.6877536}, {"type": "node", "id": 8894991465, "lat": 9.5322741, "lon": 46.6877587}, {"type": "node", "id": 8894991466, "lat": 9.5322763, "lon": 46.6877782}, {"type": "node", "id": 8894991467, "lat": 9.5322688, "lon": 46.6877852}, {"type": "node", "id": 8894991468, "lat": 9.5322587, "lon": 46.6877864}, {"type": "node", "id": 8894991469, "lat": 9.5322498, "lon": 46.6877813}, {"type": "node", "id": 8894991470, "lat": 9.5322456, "lon": 46.6877719}, {"type": "node", "id": 8894991471, "lat": 9.5322784, "lon": 46.6877681}, {"type": "node", "id": 8894991620, "lat": 9.5457381, "lon": 46.6955687}, {"type": "node", "id": 8894991621, "lat": 9.5457432, "lon": 46.6955578}, {"type": "node", "id": 8894991622, "lat": 9.5457537, "lon": 46.6955521}, {"type": "node", "id": 8894991623, "lat": 9.5457655, "lon": 46.6955537}, {"type": "node", "id": 8894991624, "lat": 9.5457763, "lon": 46.6955739}, {"type": "node", "id": 8894991625, "lat": 9.5457711, "lon": 46.6955848}, {"type": "node", "id": 8894991626, "lat": 9.5457607, "lon": 46.6955905}, {"type": "node", "id": 8894991627, "lat": 9.5457489, "lon": 46.6955889}, {"type": "node", "id": 8894991628, "lat": 9.5457402, "lon": 46.6955806}, {"type": "node", "id": 8894991629, "lat": 9.5457741, "lon": 46.695562}, {"type": "node", "id": 8894991630, "lat": 9.5459695, "lon": 46.6955643}, {"type": "node", "id": 8894991631, "lat": 9.5459751, "lon": 46.6955606}, {"type": "node", "id": 8894991632, "lat": 9.5459813, "lon": 46.6955704}, {"type": "node", "id": 8894991633, "lat": 9.5459758, "lon": 46.6955741}, {"type": "node", "id": 8894991634, "lat": 9.5459699, "lon": 46.695571}, {"type": "node", "id": 8894991635, "lat": 9.545981, "lon": 46.6955637}, {"type": "node", "id": 8894991636, "lat": 9.5459629, "lon": 46.6955607}, {"type": "node", "id": 8894991637, "lat": 9.5459351, "lon": 46.6955596}, {"type": "node", "id": 8894991638, "lat": 9.545936, "lon": 46.6955389}, {"type": "node", "id": 8894991639, "lat": 9.5459638, "lon": 46.69554}, {"type": "node", "id": 8894991641, "lat": 9.5420301, "lon": 46.6972721}, {"type": "node", "id": 8894991642, "lat": 9.542038, "lon": 46.6972632}, {"type": "node", "id": 8894991643, "lat": 9.5420498, "lon": 46.6972625}, {"type": "node", "id": 8894991644, "lat": 9.5420592, "lon": 46.6972825}, {"type": "node", "id": 8894991645, "lat": 9.5420513, "lon": 46.6972914}, {"type": "node", "id": 8894991646, "lat": 9.5420395, "lon": 46.697292}, {"type": "node", "id": 8894991647, "lat": 9.5420307, "lon": 46.697284}, {"type": "node", "id": 8894991648, "lat": 9.5420585, "lon": 46.6972705}, {"type": "node", "id": 8894991649, "lat": 9.5421096, "lon": 46.6973842}, {"type": "node", "id": 8894991650, "lat": 9.5421175, "lon": 46.6973776}, {"type": "node", "id": 8894991651, "lat": 9.5421277, "lon": 46.6973787}, {"type": "node", "id": 8894991652, "lat": 9.5421332, "lon": 46.697397}, {"type": "node", "id": 8894991653, "lat": 9.5421253, "lon": 46.6974036}, {"type": "node", "id": 8894991654, "lat": 9.5421151, "lon": 46.6974026}, {"type": "node", "id": 8894991655, "lat": 9.5421086, "lon": 46.6973946}, {"type": "node", "id": 8894991656, "lat": 9.5421342, "lon": 46.6973867}, {"type": "node", "id": 8894991659, "lat": 9.543969, "lon": 46.696299}, {"type": "node", "id": 8894991660, "lat": 9.5439746, "lon": 46.6962947}, {"type": "node", "id": 8894991661, "lat": 9.5439816, "lon": 46.6962957}, {"type": "node", "id": 8894991662, "lat": 9.5439849, "lon": 46.6963085}, {"type": "node", "id": 8894991663, "lat": 9.5439793, "lon": 46.6963128}, {"type": "node", "id": 8894991664, "lat": 9.5439723, "lon": 46.6963118}, {"type": "node", "id": 8894991665, "lat": 9.543968, "lon": 46.6963061}, {"type": "node", "id": 8894991666, "lat": 9.5439859, "lon": 46.6963014}, {"type": "node", "id": 8894991667, "lat": 9.544017, "lon": 46.6962585}, {"type": "node", "id": 8894991668, "lat": 9.5440223, "lon": 46.69625}, {"type": "node", "id": 8894991669, "lat": 9.5440314, "lon": 46.6962463}, {"type": "node", "id": 8894991670, "lat": 9.544041, "lon": 46.6962488}, {"type": "node", "id": 8894991671, "lat": 9.544048, "lon": 46.6962665}, {"type": "node", "id": 8894991672, "lat": 9.5440428, "lon": 46.696275}, {"type": "node", "id": 8894991673, "lat": 9.5440336, "lon": 46.6962787}, {"type": "node", "id": 8894991674, "lat": 9.544024, "lon": 46.6962763}, {"type": "node", "id": 8894991675, "lat": 9.5440176, "lon": 46.6962685}, {"type": "node", "id": 8894991676, "lat": 9.5440474, "lon": 46.6962565}, {"type": "node", "id": 8901544518, "lat": 9.4900874, "lon": 46.8310728}, {"type": "node", "id": 8901544519, "lat": 9.4900843, "lon": 46.8310999}, {"type": "node", "id": 8901544520, "lat": 9.4900995, "lon": 46.8311018}, {"type": "node", "id": 8901544521, "lat": 9.4901027, "lon": 46.8310746}, {"type": "node", "id": 8901544522, "lat": 9.4900501, "lon": 46.8310563}, {"type": "node", "id": 8901544523, "lat": 9.4900509, "lon": 46.8310826}, {"type": "node", "id": 8901544524, "lat": 9.4900759, "lon": 46.8310818}, {"type": "node", "id": 8901544525, "lat": 9.4900751, "lon": 46.8310555}, {"type": "node", "id": 8901544526, "lat": 9.4901648, "lon": 46.8309989}, {"type": "node", "id": 8901544527, "lat": 9.4901648, "lon": 46.8310483}, {"type": "node", "id": 8901544528, "lat": 9.4902049, "lon": 46.8310483}, {"type": "node", "id": 8901544529, "lat": 9.4902049, "lon": 46.8309989}, {"type": "node", "id": 8901544592, "lat": 9.4882888, "lon": 46.8302555}, {"type": "node", "id": 8901544593, "lat": 9.4882656, "lon": 46.8303051}, {"type": "node", "id": 8901544594, "lat": 9.4883037, "lon": 46.8303233}, {"type": "node", "id": 8901544595, "lat": 9.4883268, "lon": 46.8302737}, {"type": "node", "id": 8901544745, "lat": 9.5232477, "lon": 46.7415224}, {"type": "node", "id": 8901544746, "lat": 9.5232559, "lon": 46.7415176}, {"type": "node", "id": 8901544747, "lat": 9.523265, "lon": 46.74152}, {"type": "node", "id": 8901544748, "lat": 9.5232674, "lon": 46.7415375}, {"type": "node", "id": 8901544749, "lat": 9.5232592, "lon": 46.7415424}, {"type": "node", "id": 8901544750, "lat": 9.5232501, "lon": 46.7415399}, {"type": "node", "id": 8901544751, "lat": 9.5232453, "lon": 46.7415317}, {"type": "node", "id": 8901544752, "lat": 9.5232698, "lon": 46.7415283}, {"type": "node", "id": 8901544753, "lat": 9.5231804, "lon": 46.7415006}, {"type": "node", "id": 8901544754, "lat": 9.5231891, "lon": 46.7414928}, {"type": "node", "id": 8901544755, "lat": 9.5232008, "lon": 46.7414935}, {"type": "node", "id": 8901544756, "lat": 9.5232079, "lon": 46.7415142}, {"type": "node", "id": 8901544757, "lat": 9.5231991, "lon": 46.7415221}, {"type": "node", "id": 8901544758, "lat": 9.5231874, "lon": 46.7415214}, {"type": "node", "id": 8901544759, "lat": 9.5231797, "lon": 46.7415125}, {"type": "node", "id": 8901544760, "lat": 9.5232086, "lon": 46.7415023}, {"type": "node", "id": 8901544761, "lat": 9.523199, "lon": 46.7415622}, {"type": "node", "id": 8901544762, "lat": 9.5232044, "lon": 46.7415496}, {"type": "node", "id": 8901544763, "lat": 9.5232161, "lon": 46.7415426}, {"type": "node", "id": 8901544764, "lat": 9.5232296, "lon": 46.741544}, {"type": "node", "id": 8901544765, "lat": 9.5232427, "lon": 46.7415665}, {"type": "node", "id": 8901544766, "lat": 9.5232372, "lon": 46.7415791}, {"type": "node", "id": 8901544767, "lat": 9.5232256, "lon": 46.7415861}, {"type": "node", "id": 8901544768, "lat": 9.5232121, "lon": 46.7415848}, {"type": "node", "id": 8901544769, "lat": 9.5232019, "lon": 46.7415756}, {"type": "node", "id": 8901544770, "lat": 9.5232397, "lon": 46.7415531}, {"type": "node", "id": 8901544771, "lat": 9.5232602, "lon": 46.7415549}, {"type": "node", "id": 8901544772, "lat": 9.5232686, "lon": 46.7415486}, {"type": "node", "id": 8901544773, "lat": 9.5232791, "lon": 46.7415501}, {"type": "node", "id": 8901544774, "lat": 9.5232838, "lon": 46.7415693}, {"type": "node", "id": 8901544775, "lat": 9.5232753, "lon": 46.7415756}, {"type": "node", "id": 8901544776, "lat": 9.5232649, "lon": 46.7415741}, {"type": "node", "id": 8901544777, "lat": 9.5232586, "lon": 46.7415655}, {"type": "node", "id": 8901544778, "lat": 9.5232853, "lon": 46.7415587}, {"type": "node", "id": 8901544779, "lat": 9.5233049, "lon": 46.7415949}, {"type": "node", "id": 8901544780, "lat": 9.5233136, "lon": 46.7415876}, {"type": "node", "id": 8901544781, "lat": 9.523325, "lon": 46.7415869}, {"type": "node", "id": 8901544782, "lat": 9.5233346, "lon": 46.7415931}, {"type": "node", "id": 8901544783, "lat": 9.5233359, "lon": 46.741615}, {"type": "node", "id": 8901544784, "lat": 9.5233271, "lon": 46.7416223}, {"type": "node", "id": 8901544785, "lat": 9.5233157, "lon": 46.741623}, {"type": "node", "id": 8901544786, "lat": 9.5233062, "lon": 46.7416168}, {"type": "node", "id": 8901544787, "lat": 9.523302, "lon": 46.7416061}, {"type": "node", "id": 8901544788, "lat": 9.5233387, "lon": 46.7416038}, {"type": "node", "id": 8901544821, "lat": 9.4997894, "lon": 46.7430179}, {"type": "node", "id": 8901544822, "lat": 9.4997926, "lon": 46.7430082}, {"type": "node", "id": 8901544823, "lat": 9.4998009, "lon": 46.7430023}, {"type": "node", "id": 8901544824, "lat": 9.499811, "lon": 46.7430024}, {"type": "node", "id": 8901544825, "lat": 9.4998221, "lon": 46.7430184}, {"type": "node", "id": 8901544826, "lat": 9.4998188, "lon": 46.7430281}, {"type": "node", "id": 8901544827, "lat": 9.4998106, "lon": 46.743034}, {"type": "node", "id": 8901544828, "lat": 9.4998005, "lon": 46.7430338}, {"type": "node", "id": 8901544829, "lat": 9.4997924, "lon": 46.7430277}, {"type": "node", "id": 8901544830, "lat": 9.4998191, "lon": 46.7430086}, {"type": "node", "id": 8903274087, "lat": 9.4484907, "lon": 46.9168659}, {"type": "node", "id": 8903274088, "lat": 9.4484984, "lon": 46.9168563}, {"type": "node", "id": 8903274089, "lat": 9.4485103, "lon": 46.916853}, {"type": "node", "id": 8903274090, "lat": 9.4485218, "lon": 46.9168575}, {"type": "node", "id": 8903274091, "lat": 9.4485278, "lon": 46.9168804}, {"type": "node", "id": 8903274092, "lat": 9.4485201, "lon": 46.91689}, {"type": "node", "id": 8903274093, "lat": 9.4485082, "lon": 46.9168932}, {"type": "node", "id": 8903274094, "lat": 9.4484968, "lon": 46.9168888}, {"type": "node", "id": 8903274095, "lat": 9.4484901, "lon": 46.9168784}, {"type": "node", "id": 8903274096, "lat": 9.4485284, "lon": 46.9168679}, {"type": "node", "id": 8903917677, "lat": 9.4283676, "lon": 46.8073071}, {"type": "node", "id": 8903917678, "lat": 9.4283787, "lon": 46.8072971}, {"type": "node", "id": 8903917679, "lat": 9.4283935, "lon": 46.8072956}, {"type": "node", "id": 8903917680, "lat": 9.4284062, "lon": 46.8073032}, {"type": "node", "id": 8903917681, "lat": 9.428409, "lon": 46.8073317}, {"type": "node", "id": 8903917682, "lat": 9.4283979, "lon": 46.8073416}, {"type": "node", "id": 8903917683, "lat": 9.4283832, "lon": 46.8073431}, {"type": "node", "id": 8903917684, "lat": 9.4283704, "lon": 46.8073355}, {"type": "node", "id": 8903917685, "lat": 9.4283645, "lon": 46.8073217}, {"type": "node", "id": 8903917686, "lat": 9.4284122, "lon": 46.807317}, {"type": "node", "id": 8903917785, "lat": 9.4324808, "lon": 46.8028408}, {"type": "node", "id": 8903917786, "lat": 9.4324854, "lon": 46.8028328}, {"type": "node", "id": 8903917787, "lat": 9.4324942, "lon": 46.8028304}, {"type": "node", "id": 8903917788, "lat": 9.4325044, "lon": 46.802844}, {"type": "node", "id": 8903917789, "lat": 9.4324998, "lon": 46.802852}, {"type": "node", "id": 8903917790, "lat": 9.432491, "lon": 46.8028544}, {"type": "node", "id": 8903917791, "lat": 9.4324832, "lon": 46.8028497}, {"type": "node", "id": 8903917792, "lat": 9.4325021, "lon": 46.8028351}, {"type": "node", "id": 8903917793, "lat": 9.4324548, "lon": 46.8028226}, {"type": "node", "id": 8903917794, "lat": 9.4324592, "lon": 46.8028142}, {"type": "node", "id": 8903917795, "lat": 9.4324682, "lon": 46.8028114}, {"type": "node", "id": 8903917796, "lat": 9.4324792, "lon": 46.802825}, {"type": "node", "id": 8903917797, "lat": 9.4324748, "lon": 46.8028334}, {"type": "node", "id": 8903917798, "lat": 9.4324658, "lon": 46.8028361}, {"type": "node", "id": 8903917799, "lat": 9.4324576, "lon": 46.8028317}, {"type": "node", "id": 8903917800, "lat": 9.4324765, "lon": 46.8028159}, {"type": "node", "id": 8903917811, "lat": 9.4316232, "lon": 46.8097081}, {"type": "node", "id": 8903917812, "lat": 9.4316341, "lon": 46.8097043}, {"type": "node", "id": 8903917813, "lat": 9.4316451, "lon": 46.8097078}, {"type": "node", "id": 8903917814, "lat": 9.431652, "lon": 46.8097172}, {"type": "node", "id": 8903917815, "lat": 9.4316455, "lon": 46.8097384}, {"type": "node", "id": 8903917816, "lat": 9.4316345, "lon": 46.8097421}, {"type": "node", "id": 8903917817, "lat": 9.4316235, "lon": 46.8097387}, {"type": "node", "id": 8903917818, "lat": 9.4316167, "lon": 46.8097293}, {"type": "node", "id": 8903917819, "lat": 9.4316165, "lon": 46.8097176}, {"type": "node", "id": 8903917820, "lat": 9.4316521, "lon": 46.8097289}, {"type": "node", "id": 8903917821, "lat": 9.4316218, "lon": 46.8096655}, {"type": "node", "id": 8903917822, "lat": 9.4316304, "lon": 46.8096595}, {"type": "node", "id": 8903917823, "lat": 9.4316407, "lon": 46.8096615}, {"type": "node", "id": 8903917824, "lat": 9.4316446, "lon": 46.8096806}, {"type": "node", "id": 8903917825, "lat": 9.431636, "lon": 46.8096866}, {"type": "node", "id": 8903917826, "lat": 9.4316257, "lon": 46.8096846}, {"type": "node", "id": 8903917827, "lat": 9.4316199, "lon": 46.8096759}, {"type": "node", "id": 8903917828, "lat": 9.4316466, "lon": 46.8096702}, {"type": "node", "id": 8903917829, "lat": 9.4316443, "lon": 46.8098427}, {"type": "node", "id": 8903917830, "lat": 9.4316529, "lon": 46.8098363}, {"type": "node", "id": 8903917831, "lat": 9.4316636, "lon": 46.8098363}, {"type": "node", "id": 8903917832, "lat": 9.4316722, "lon": 46.8098427}, {"type": "node", "id": 8903917833, "lat": 9.4316722, "lon": 46.8098632}, {"type": "node", "id": 8903917834, "lat": 9.4316636, "lon": 46.8098695}, {"type": "node", "id": 8903917835, "lat": 9.4316529, "lon": 46.8098695}, {"type": "node", "id": 8903917836, "lat": 9.4316443, "lon": 46.8098632}, {"type": "node", "id": 8903917837, "lat": 9.431641, "lon": 46.8098529}, {"type": "node", "id": 8903917838, "lat": 9.4316755, "lon": 46.8098529}, {"type": "node", "id": 8903917846, "lat": 9.4333405, "lon": 46.8119998}, {"type": "node", "id": 8903917847, "lat": 9.4333484, "lon": 46.8119933}, {"type": "node", "id": 8903917848, "lat": 9.4333586, "lon": 46.8119928}, {"type": "node", "id": 8903917849, "lat": 9.4333672, "lon": 46.8119985}, {"type": "node", "id": 8903917850, "lat": 9.4333681, "lon": 46.8120182}, {"type": "node", "id": 8903917851, "lat": 9.4333601, "lon": 46.8120247}, {"type": "node", "id": 8903917852, "lat": 9.4333499, "lon": 46.8120252}, {"type": "node", "id": 8903917853, "lat": 9.4333414, "lon": 46.8120195}, {"type": "node", "id": 8903917854, "lat": 9.4333378, "lon": 46.8120098}, {"type": "node", "id": 8903917855, "lat": 9.4333708, "lon": 46.8120082}, {"type": "node", "id": 8903917856, "lat": 9.4334336, "lon": 46.8119255}, {"type": "node", "id": 8903917857, "lat": 9.4334423, "lon": 46.8119184}, {"type": "node", "id": 8903917858, "lat": 9.4334535, "lon": 46.8119179}, {"type": "node", "id": 8903917859, "lat": 9.4334629, "lon": 46.8119242}, {"type": "node", "id": 8903917860, "lat": 9.4334638, "lon": 46.8119458}, {"type": "node", "id": 8903917861, "lat": 9.433455, "lon": 46.8119528}, {"type": "node", "id": 8903917862, "lat": 9.4334438, "lon": 46.8119533}, {"type": "node", "id": 8903917863, "lat": 9.4334345, "lon": 46.8119471}, {"type": "node", "id": 8903917864, "lat": 9.4334306, "lon": 46.8119364}, {"type": "node", "id": 8903917865, "lat": 9.4334668, "lon": 46.8119348}, {"type": "node", "id": 8903917871, "lat": 9.41786, "lon": 46.8029329}, {"type": "node", "id": 8903917872, "lat": 9.4178687, "lon": 46.8029278}, {"type": "node", "id": 8903917873, "lat": 9.4178786, "lon": 46.8029289}, {"type": "node", "id": 8903917874, "lat": 9.4178861, "lon": 46.8029356}, {"type": "node", "id": 8903917875, "lat": 9.4178841, "lon": 46.8029549}, {"type": "node", "id": 8903917876, "lat": 9.4178755, "lon": 46.80296}, {"type": "node", "id": 8903917877, "lat": 9.4178655, "lon": 46.8029589}, {"type": "node", "id": 8903917878, "lat": 9.417858, "lon": 46.8029521}, {"type": "node", "id": 8903917879, "lat": 9.4178559, "lon": 46.8029422}, {"type": "node", "id": 8903917880, "lat": 9.4178882, "lon": 46.8029456}, {"type": "node", "id": 8904548569, "lat": 9.3770508, "lon": 46.8608284}, {"type": "node", "id": 8904548570, "lat": 9.3770626, "lon": 46.8608208}, {"type": "node", "id": 8904548571, "lat": 9.3770765, "lon": 46.8608216}, {"type": "node", "id": 8904548572, "lat": 9.3770872, "lon": 46.8608305}, {"type": "node", "id": 8904548573, "lat": 9.3770857, "lon": 46.8608573}, {"type": "node", "id": 8904548574, "lat": 9.377074, "lon": 46.8608649}, {"type": "node", "id": 8904548575, "lat": 9.3770601, "lon": 46.8608641}, {"type": "node", "id": 8904548576, "lat": 9.3770493, "lon": 46.8608552}, {"type": "node", "id": 8904548577, "lat": 9.3770458, "lon": 46.8608415}, {"type": "node", "id": 8904548578, "lat": 9.3770908, "lon": 46.8608442}, {"type": "node", "id": 8904548579, "lat": 9.3772228, "lon": 46.8607886}, {"type": "node", "id": 8904548580, "lat": 9.3772322, "lon": 46.8607795}, {"type": "node", "id": 8904548581, "lat": 9.3772449, "lon": 46.8607765}, {"type": "node", "id": 8904548582, "lat": 9.3772574, "lon": 46.8607802}, {"type": "node", "id": 8904548583, "lat": 9.3772664, "lon": 46.8607898}, {"type": "node", "id": 8904548584, "lat": 9.3772657, "lon": 46.8608153}, {"type": "node", "id": 8904548585, "lat": 9.3772562, "lon": 46.8608244}, {"type": "node", "id": 8904548586, "lat": 9.3772436, "lon": 46.8608274}, {"type": "node", "id": 8904548587, "lat": 9.3772311, "lon": 46.8608237}, {"type": "node", "id": 8904548588, "lat": 9.3772221, "lon": 46.8608141}, {"type": "node", "id": 8904548589, "lat": 9.3772191, "lon": 46.8608013}, {"type": "node", "id": 8904548590, "lat": 9.3772694, "lon": 46.8608026}, {"type": "node", "id": 8907426166, "lat": 9.3906056, "lon": 46.8872218}, {"type": "node", "id": 8907426167, "lat": 9.3906147, "lon": 46.8872161}, {"type": "node", "id": 8907426168, "lat": 9.3906253, "lon": 46.8872169}, {"type": "node", "id": 8907426169, "lat": 9.3906334, "lon": 46.8872239}, {"type": "node", "id": 8907426170, "lat": 9.3906319, "lon": 46.8872444}, {"type": "node", "id": 8907426171, "lat": 9.3906228, "lon": 46.8872501}, {"type": "node", "id": 8907426172, "lat": 9.3906122, "lon": 46.8872493}, {"type": "node", "id": 8907426173, "lat": 9.390604, "lon": 46.8872423}, {"type": "node", "id": 8907426174, "lat": 9.3906015, "lon": 46.8872318}, {"type": "node", "id": 8907426175, "lat": 9.3906359, "lon": 46.8872344}, {"type": "node", "id": 8907426176, "lat": 9.3906409, "lon": 46.887034}, {"type": "node", "id": 8907426177, "lat": 9.3906512, "lon": 46.8870258}, {"type": "node", "id": 8907426178, "lat": 9.3906643, "lon": 46.8870254}, {"type": "node", "id": 8907426179, "lat": 9.3906752, "lon": 46.8870329}, {"type": "node", "id": 8907426180, "lat": 9.3906759, "lon": 46.8870581}, {"type": "node", "id": 8907426181, "lat": 9.3906656, "lon": 46.8870662}, {"type": "node", "id": 8907426182, "lat": 9.3906525, "lon": 46.8870666}, {"type": "node", "id": 8907426183, "lat": 9.3906417, "lon": 46.8870592}, {"type": "node", "id": 8907426184, "lat": 9.3906372, "lon": 46.8870467}, {"type": "node", "id": 8907426185, "lat": 9.3906796, "lon": 46.8870454}, {"type": "node", "id": 8909742980, "lat": 9.3473889, "lon": 46.7727788}, {"type": "node", "id": 8909742981, "lat": 9.3472888, "lon": 46.7727281}, {"type": "node", "id": 8909742982, "lat": 9.3472587, "lon": 46.772789}, {"type": "node", "id": 8909742983, "lat": 9.3473589, "lon": 46.7728397}, {"type": "node", "id": 8909795561, "lat": 9.259858, "lon": 46.816413}, {"type": "node", "id": 8909795562, "lat": 9.2598594, "lon": 46.816403}, {"type": "node", "id": 8909795563, "lat": 9.2598663, "lon": 46.8163957}, {"type": "node", "id": 8909795564, "lat": 9.2598762, "lon": 46.816394}, {"type": "node", "id": 8909795565, "lat": 9.2598898, "lon": 46.8164073}, {"type": "node", "id": 8909795566, "lat": 9.2598884, "lon": 46.8164174}, {"type": "node", "id": 8909795567, "lat": 9.2598815, "lon": 46.8164246}, {"type": "node", "id": 8909795568, "lat": 9.2598717, "lon": 46.8164264}, {"type": "node", "id": 8909795569, "lat": 9.2598627, "lon": 46.8164219}, {"type": "node", "id": 8909795570, "lat": 9.2598851, "lon": 46.8163984}, {"type": "node", "id": 8909795571, "lat": 9.2599043, "lon": 46.8164461}, {"type": "node", "id": 8909795572, "lat": 9.2599056, "lon": 46.8164354}, {"type": "node", "id": 8909795573, "lat": 9.2599127, "lon": 46.8164275}, {"type": "node", "id": 8909795574, "lat": 9.2599231, "lon": 46.8164254}, {"type": "node", "id": 8909795575, "lat": 9.2599379, "lon": 46.8164393}, {"type": "node", "id": 8909795576, "lat": 9.2599367, "lon": 46.8164499}, {"type": "node", "id": 8909795577, "lat": 9.2599295, "lon": 46.8164578}, {"type": "node", "id": 8909795578, "lat": 9.2599191, "lon": 46.8164599}, {"type": "node", "id": 8909795579, "lat": 9.2599095, "lon": 46.8164554}, {"type": "node", "id": 8909795580, "lat": 9.2599327, "lon": 46.8164299}, {"type": "node", "id": 8909860600, "lat": 9.2303384, "lon": 46.8330342}, {"type": "node", "id": 8909860601, "lat": 9.2303449, "lon": 46.8330255}, {"type": "node", "id": 8909860602, "lat": 9.2303556, "lon": 46.8330241}, {"type": "node", "id": 8909860603, "lat": 9.2303656, "lon": 46.8330416}, {"type": "node", "id": 8909860604, "lat": 9.2303591, "lon": 46.8330503}, {"type": "node", "id": 8909860605, "lat": 9.2303484, "lon": 46.8330517}, {"type": "node", "id": 8909860606, "lat": 9.2303398, "lon": 46.8330451}, {"type": "node", "id": 8909860607, "lat": 9.2303642, "lon": 46.8330307}, {"type": "node", "id": 8909860608, "lat": 9.2303508, "lon": 46.833065}, {"type": "node", "id": 8909860609, "lat": 9.2303581, "lon": 46.8330575}, {"type": "node", "id": 8909860610, "lat": 9.2303683, "lon": 46.8330558}, {"type": "node", "id": 8909860611, "lat": 9.2303775, "lon": 46.8330605}, {"type": "node", "id": 8909860612, "lat": 9.2303808, "lon": 46.8330802}, {"type": "node", "id": 8909860613, "lat": 9.2303735, "lon": 46.8330877}, {"type": "node", "id": 8909860614, "lat": 9.2303633, "lon": 46.8330894}, {"type": "node", "id": 8909860615, "lat": 9.230354, "lon": 46.8330847}, {"type": "node", "id": 8909860616, "lat": 9.2303493, "lon": 46.8330754}, {"type": "node", "id": 8909871017, "lat": 9.2303823, "lon": 46.8330698}, {"type": "node", "id": 8910152716, "lat": 9.2114146, "lon": 46.8443961}, {"type": "node", "id": 8910222017, "lat": 9.2114217, "lon": 46.8443904}, {"type": "node", "id": 8910222018, "lat": 9.2114307, "lon": 46.8443916}, {"type": "node", "id": 8910222019, "lat": 9.2114352, "lon": 46.8444079}, {"type": "node", "id": 8910222020, "lat": 9.211428, "lon": 46.8444136}, {"type": "node", "id": 8910222021, "lat": 9.211419, "lon": 46.8444124}, {"type": "node", "id": 8910222022, "lat": 9.2114135, "lon": 46.8444052}, {"type": "node", "id": 8910222023, "lat": 9.2114363, "lon": 46.8443988}, {"type": "node", "id": 8910222024, "lat": 9.2114562, "lon": 46.8444318}, {"type": "node", "id": 8910222025, "lat": 9.2114666, "lon": 46.8444271}, {"type": "node", "id": 8910222026, "lat": 9.2114773, "lon": 46.8444313}, {"type": "node", "id": 8910222027, "lat": 9.2114779, "lon": 46.8444527}, {"type": "node", "id": 8910222028, "lat": 9.2114674, "lon": 46.8444574}, {"type": "node", "id": 8910222029, "lat": 9.2114567, "lon": 46.8444533}, {"type": "node", "id": 8910222030, "lat": 9.211452, "lon": 46.8444427}, {"type": "node", "id": 8910222031, "lat": 9.211482, "lon": 46.8444419}, {"type": "node", "id": 8910222155, "lat": 9.2368925, "lon": 46.8323017}, {"type": "node", "id": 8910222156, "lat": 9.2369017, "lon": 46.8322962}, {"type": "node", "id": 8910222157, "lat": 9.2369123, "lon": 46.8322973}, {"type": "node", "id": 8910222158, "lat": 9.2369204, "lon": 46.8323045}, {"type": "node", "id": 8910222159, "lat": 9.2369184, "lon": 46.832325}, {"type": "node", "id": 8910222160, "lat": 9.2369092, "lon": 46.8323305}, {"type": "node", "id": 8910222161, "lat": 9.2368985, "lon": 46.8323295}, {"type": "node", "id": 8910222162, "lat": 9.2368905, "lon": 46.8323223}, {"type": "node", "id": 8910222163, "lat": 9.2368882, "lon": 46.8323117}, {"type": "node", "id": 8910222164, "lat": 9.2369227, "lon": 46.8323151}, {"type": "node", "id": 8910222165, "lat": 9.2369966, "lon": 46.8321925}, {"type": "node", "id": 8910222166, "lat": 9.2370064, "lon": 46.832183}, {"type": "node", "id": 8910222167, "lat": 9.2370195, "lon": 46.8321797}, {"type": "node", "id": 8910222168, "lat": 9.2370325, "lon": 46.8321836}, {"type": "node", "id": 8910222169, "lat": 9.2370419, "lon": 46.8321935}, {"type": "node", "id": 8910222170, "lat": 9.2370413, "lon": 46.83222}, {"type": "node", "id": 8910222171, "lat": 9.2370316, "lon": 46.8322295}, {"type": "node", "id": 8910222172, "lat": 9.2370184, "lon": 46.8322327}, {"type": "node", "id": 8910222173, "lat": 9.2370054, "lon": 46.8322289}, {"type": "node", "id": 8910222174, "lat": 9.236996, "lon": 46.832219}, {"type": "node", "id": 8910222175, "lat": 9.2369928, "lon": 46.8322057}, {"type": "node", "id": 8910222176, "lat": 9.2370451, "lon": 46.8322068}, {"type": "node", "id": 8911977799, "lat": 9.1885228, "lon": 46.7815946}, {"type": "node", "id": 8911977800, "lat": 9.1885276, "lon": 46.7815845}, {"type": "node", "id": 8911977801, "lat": 9.1885373, "lon": 46.7815791}, {"type": "node", "id": 8911977802, "lat": 9.1885483, "lon": 46.7815806}, {"type": "node", "id": 8911977803, "lat": 9.1885584, "lon": 46.7815993}, {"type": "node", "id": 8911977804, "lat": 9.1885536, "lon": 46.7816094}, {"type": "node", "id": 8911977805, "lat": 9.1885439, "lon": 46.7816148}, {"type": "node", "id": 8911977806, "lat": 9.1885329, "lon": 46.7816134}, {"type": "node", "id": 8911977807, "lat": 9.1885249, "lon": 46.7816057}, {"type": "node", "id": 8911977808, "lat": 9.1885563, "lon": 46.7815883}, {"type": "node", "id": 8911977809, "lat": 9.1884969, "lon": 46.7817243}, {"type": "node", "id": 8911977810, "lat": 9.1885023, "lon": 46.7817127}, {"type": "node", "id": 8911977811, "lat": 9.1885134, "lon": 46.7817066}, {"type": "node", "id": 8911977812, "lat": 9.188526, "lon": 46.7817082}, {"type": "node", "id": 8911977813, "lat": 9.1885375, "lon": 46.7817296}, {"type": "node", "id": 8911977814, "lat": 9.1885321, "lon": 46.7817412}, {"type": "node", "id": 8911977815, "lat": 9.188521, "lon": 46.7817473}, {"type": "node", "id": 8911977816, "lat": 9.1885084, "lon": 46.7817457}, {"type": "node", "id": 8911997517, "lat": 9.1884993, "lon": 46.7817369}, {"type": "node", "id": 8911997518, "lat": 9.1885351, "lon": 46.781717}, {"type": "node", "id": 8932937502, "lat": 9.1860412, "lon": 46.6740902}, {"type": "node", "id": 8932937503, "lat": 9.1859249, "lon": 46.6739676}, {"type": "node", "id": 8932937504, "lat": 9.1859828, "lon": 46.6739112}, {"type": "node", "id": 8932937505, "lat": 9.1860991, "lon": 46.6740338}, {"type": "node", "id": 8932937506, "lat": 9.1860458, "lon": 46.6740906}, {"type": "node", "id": 8932937507, "lat": 9.1861159, "lon": 46.6741631}, {"type": "node", "id": 8932937508, "lat": 9.1861773, "lon": 46.6741021}, {"type": "node", "id": 8932937509, "lat": 9.1861071, "lon": 46.6740297}, {"type": "node", "id": 8933105221, "lat": 9.2169186, "lon": 46.7659816}, {"type": "node", "id": 8933105222, "lat": 9.21693, "lon": 46.7659751}, {"type": "node", "id": 8933105223, "lat": 9.216943, "lon": 46.7659765}, {"type": "node", "id": 8933105224, "lat": 9.2169527, "lon": 46.7659854}, {"type": "node", "id": 8933105225, "lat": 9.21695, "lon": 46.7660105}, {"type": "node", "id": 8933105226, "lat": 9.2169386, "lon": 46.7660171}, {"type": "node", "id": 8933105227, "lat": 9.2169256, "lon": 46.7660157}, {"type": "node", "id": 8933105228, "lat": 9.2169159, "lon": 46.7660067}, {"type": "node", "id": 8933105229, "lat": 9.2169132, "lon": 46.7659937}, {"type": "node", "id": 8933105230, "lat": 9.2169554, "lon": 46.7659984}, {"type": "node", "id": 8933105231, "lat": 9.2170166, "lon": 46.7659022}, {"type": "node", "id": 8933105232, "lat": 9.2170253, "lon": 46.7658955}, {"type": "node", "id": 8933105233, "lat": 9.2170363, "lon": 46.7658952}, {"type": "node", "id": 8933105234, "lat": 9.2170454, "lon": 46.7659016}, {"type": "node", "id": 8933105235, "lat": 9.2170458, "lon": 46.7659228}, {"type": "node", "id": 8933105236, "lat": 9.217037, "lon": 46.7659295}, {"type": "node", "id": 8933105237, "lat": 9.217026, "lon": 46.7659297}, {"type": "node", "id": 8933105238, "lat": 9.217017, "lon": 46.7659234}, {"type": "node", "id": 8933105239, "lat": 9.2170134, "lon": 46.7659128}, {"type": "node", "id": 8933105240, "lat": 9.217049, "lon": 46.7659121}, {"type": "node", "id": 8933155949, "lat": 9.2500577, "lon": 46.7332371}, {"type": "node", "id": 8933155950, "lat": 9.2500681, "lon": 46.7332265}, {"type": "node", "id": 8933155951, "lat": 9.2500823, "lon": 46.7332227}, {"type": "node", "id": 8933155952, "lat": 9.2500966, "lon": 46.7332265}, {"type": "node", "id": 8933155953, "lat": 9.250107, "lon": 46.7332371}, {"type": "node", "id": 8933155954, "lat": 9.250107, "lon": 46.7332659}, {"type": "node", "id": 8933155955, "lat": 9.2500966, "lon": 46.7332765}, {"type": "node", "id": 8933155956, "lat": 9.2500823, "lon": 46.7332803}, {"type": "node", "id": 8933155957, "lat": 9.2500681, "lon": 46.7332765}, {"type": "node", "id": 8933155958, "lat": 9.2500577, "lon": 46.7332659}, {"type": "node", "id": 8933155959, "lat": 9.2500539, "lon": 46.7332515}, {"type": "node", "id": 8933155960, "lat": 9.2501108, "lon": 46.7332515}, {"type": "node", "id": 8933155961, "lat": 9.2501468, "lon": 46.7332368}, {"type": "node", "id": 8933155962, "lat": 9.2501588, "lon": 46.7332275}, {"type": "node", "id": 8933155963, "lat": 9.250174, "lon": 46.733227}, {"type": "node", "id": 8933155964, "lat": 9.2501865, "lon": 46.7332357}, {"type": "node", "id": 8933155965, "lat": 9.2501872, "lon": 46.7332649}, {"type": "node", "id": 8933155966, "lat": 9.2501752, "lon": 46.7332742}, {"type": "node", "id": 8933155967, "lat": 9.2501601, "lon": 46.7332746}, {"type": "node", "id": 8933155968, "lat": 9.2501476, "lon": 46.733266}, {"type": "node", "id": 8933155969, "lat": 9.2501426, "lon": 46.7332515}, {"type": "node", "id": 8933155970, "lat": 9.2501915, "lon": 46.7332502}, {"type": "node", "id": 8933302077, "lat": 9.246672, "lon": 46.7828463}, {"type": "node", "id": 8933302078, "lat": 9.246679, "lon": 46.7828391}, {"type": "node", "id": 8933302079, "lat": 9.2466888, "lon": 46.7828375}, {"type": "node", "id": 8933302080, "lat": 9.2466977, "lon": 46.782842}, {"type": "node", "id": 8933302081, "lat": 9.2467009, "lon": 46.7828609}, {"type": "node", "id": 8933302082, "lat": 9.2466939, "lon": 46.7828681}, {"type": "node", "id": 8933302083, "lat": 9.2466841, "lon": 46.7828697}, {"type": "node", "id": 8933302084, "lat": 9.2466752, "lon": 46.7828652}, {"type": "node", "id": 8933302085, "lat": 9.2466706, "lon": 46.7828563}, {"type": "node", "id": 8933302086, "lat": 9.2467023, "lon": 46.7828509}, {"type": "node", "id": 8933302087, "lat": 9.2466957, "lon": 46.7829205}, {"type": "node", "id": 8933302088, "lat": 9.2467049, "lon": 46.7829122}, {"type": "node", "id": 8933302089, "lat": 9.2467172, "lon": 46.782911}, {"type": "node", "id": 8933302090, "lat": 9.2467278, "lon": 46.7829173}, {"type": "node", "id": 8933302091, "lat": 9.2467302, "lon": 46.7829409}, {"type": "node", "id": 8933302092, "lat": 9.2467209, "lon": 46.7829492}, {"type": "node", "id": 8933302093, "lat": 9.2467087, "lon": 46.7829505}, {"type": "node", "id": 8933302094, "lat": 9.246698, "lon": 46.7829442}, {"type": "node", "id": 8933302095, "lat": 9.2466931, "lon": 46.7829327}, {"type": "node", "id": 8933302096, "lat": 9.2467328, "lon": 46.7829287}, {"type": "node", "id": 9535616674, "lat": 9.1946407, "lon": 46.9703215}, {"type": "node", "id": 9535616675, "lat": 9.1946499, "lon": 46.9703152}, {"type": "node", "id": 9535616676, "lat": 9.1946609, "lon": 46.9703156}, {"type": "node", "id": 9535616677, "lat": 9.1946696, "lon": 46.9703225}, {"type": "node", "id": 9535616678, "lat": 9.1946689, "lon": 46.9703438}, {"type": "node", "id": 9535616679, "lat": 9.1946597, "lon": 46.9703501}, {"type": "node", "id": 9535616680, "lat": 9.1946486, "lon": 46.9703496}, {"type": "node", "id": 9535616681, "lat": 9.1946399, "lon": 46.9703427}, {"type": "node", "id": 9535616682, "lat": 9.1946369, "lon": 46.970332}, {"type": "node", "id": 9535616683, "lat": 9.1946727, "lon": 46.9703333}, {"type": "node", "id": 9535616684, "lat": 9.1939453, "lon": 46.9662628}, {"type": "node", "id": 9535616685, "lat": 9.1939843, "lon": 46.9662989}, {"type": "node", "id": 9535616686, "lat": 9.1940143, "lon": 46.9662657}, {"type": "node", "id": 9535616687, "lat": 9.1939753, "lon": 46.9662296}, {"type": "node", "id": 9537231498, "lat": 9.233665, "lon": 46.9639845}, {"type": "node", "id": 9537231499, "lat": 9.2336717, "lon": 46.963977}, {"type": "node", "id": 9537231500, "lat": 9.2336815, "lon": 46.9639749}, {"type": "node", "id": 9537231501, "lat": 9.2336907, "lon": 46.9639791}, {"type": "node", "id": 9537231502, "lat": 9.2336945, "lon": 46.963998}, {"type": "node", "id": 9537231503, "lat": 9.2336878, "lon": 46.9640055}, {"type": "node", "id": 9537231504, "lat": 9.233678, "lon": 46.9640076}, {"type": "node", "id": 9537231505, "lat": 9.2336688, "lon": 46.9640034}, {"type": "node", "id": 9537231506, "lat": 9.2336639, "lon": 46.9639946}, {"type": "node", "id": 9537231507, "lat": 9.2336956, "lon": 46.9639879}, {"type": "node", "id": 9537231508, "lat": 9.2336336, "lon": 46.9640949}, {"type": "node", "id": 9537231509, "lat": 9.2336445, "lon": 46.9640927}, {"type": "node", "id": 9537231510, "lat": 9.2336537, "lon": 46.9640989}, {"type": "node", "id": 9537231511, "lat": 9.2336498, "lon": 46.9641193}, {"type": "node", "id": 9537231512, "lat": 9.2336389, "lon": 46.9641215}, {"type": "node", "id": 9537231513, "lat": 9.2336297, "lon": 46.9641153}, {"type": "node", "id": 9537231514, "lat": 9.2336275, "lon": 46.9641043}, {"type": "node", "id": 9537231515, "lat": 9.2336559, "lon": 46.9641099}, {"type": "node", "id": 9537851253, "lat": 9.2888859, "lon": 46.9482447}, {"type": "node", "id": 9537851254, "lat": 9.2888917, "lon": 46.9482356}, {"type": "node", "id": 9537851255, "lat": 9.2889016, "lon": 46.9482316}, {"type": "node", "id": 9537851256, "lat": 9.288912, "lon": 46.9482344}, {"type": "node", "id": 9537851257, "lat": 9.2889194, "lon": 46.9482536}, {"type": "node", "id": 9537851258, "lat": 9.2889136, "lon": 46.9482627}, {"type": "node", "id": 9537851259, "lat": 9.2889037, "lon": 46.9482667}, {"type": "node", "id": 9537851260, "lat": 9.2888933, "lon": 46.9482639}, {"type": "node", "id": 9537851261, "lat": 9.2888865, "lon": 46.9482555}, {"type": "node", "id": 9537851262, "lat": 9.2889188, "lon": 46.9482428}, {"type": "node", "id": 9537851263, "lat": 9.2890274, "lon": 46.948125}, {"type": "node", "id": 9537851264, "lat": 9.2890348, "lon": 46.9481163}, {"type": "node", "id": 9537851265, "lat": 9.2890458, "lon": 46.9481136}, {"type": "node", "id": 9537851266, "lat": 9.2890562, "lon": 46.948118}, {"type": "node", "id": 9537851267, "lat": 9.2890611, "lon": 46.9481392}, {"type": "node", "id": 9537851268, "lat": 9.2890538, "lon": 46.9481479}, {"type": "node", "id": 9537851269, "lat": 9.2890428, "lon": 46.9481505}, {"type": "node", "id": 9537851270, "lat": 9.2890324, "lon": 46.9481461}, {"type": "node", "id": 9537851271, "lat": 9.2890265, "lon": 46.9481364}, {"type": "node", "id": 9537851272, "lat": 9.2890621, "lon": 46.9481278}, {"type": "node", "id": 9540146557, "lat": 9.3318474, "lon": 46.9331929}, {"type": "node", "id": 9540146558, "lat": 9.3318529, "lon": 46.9331845}, {"type": "node", "id": 9540146559, "lat": 9.3318622, "lon": 46.933181}, {"type": "node", "id": 9540146560, "lat": 9.3318717, "lon": 46.9331838}, {"type": "node", "id": 9540146561, "lat": 9.3318783, "lon": 46.9332016}, {"type": "node", "id": 9540146562, "lat": 9.3318728, "lon": 46.93321}, {"type": "node", "id": 9540146563, "lat": 9.3318635, "lon": 46.9332135}, {"type": "node", "id": 9540146564, "lat": 9.331854, "lon": 46.9332108}, {"type": "node", "id": 9540146565, "lat": 9.3318478, "lon": 46.9332029}, {"type": "node", "id": 9540146566, "lat": 9.3318779, "lon": 46.9331916}, {"type": "node", "id": 9540146567, "lat": 9.3318979, "lon": 46.9332693}, {"type": "node", "id": 9540146568, "lat": 9.3319039, "lon": 46.9332611}, {"type": "node", "id": 9540146569, "lat": 9.3319135, "lon": 46.9332579}, {"type": "node", "id": 9540146570, "lat": 9.3319232, "lon": 46.9332611}, {"type": "node", "id": 9540146571, "lat": 9.331929, "lon": 46.9332797}, {"type": "node", "id": 9540146572, "lat": 9.3319231, "lon": 46.933288}, {"type": "node", "id": 9540146573, "lat": 9.3319134, "lon": 46.9332911}, {"type": "node", "id": 9540146574, "lat": 9.3319038, "lon": 46.9332879}, {"type": "node", "id": 9540146575, "lat": 9.3318979, "lon": 46.9332796}, {"type": "node", "id": 9540146576, "lat": 9.3319291, "lon": 46.9332694}, {"type": "node", "id": 9540146588, "lat": 9.3096679, "lon": 46.9368261}, {"type": "node", "id": 9540146589, "lat": 9.3096715, "lon": 46.9368179}, {"type": "node", "id": 9540146590, "lat": 9.3096798, "lon": 46.9368147}, {"type": "node", "id": 9540146591, "lat": 9.309691, "lon": 46.9368268}, {"type": "node", "id": 9540146592, "lat": 9.3096874, "lon": 46.936835}, {"type": "node", "id": 9540146593, "lat": 9.3096791, "lon": 46.9368381}, {"type": "node", "id": 9540146594, "lat": 9.309671, "lon": 46.9368345}, {"type": "node", "id": 9540146595, "lat": 9.3096878, "lon": 46.9368184}, {"type": "node", "id": 9540146596, "lat": 9.3096754, "lon": 46.9368486}, {"type": "node", "id": 9540146597, "lat": 9.3096869, "lon": 46.936847}, {"type": "node", "id": 9540146598, "lat": 9.3096962, "lon": 46.9368541}, {"type": "node", "id": 9540146599, "lat": 9.3096908, "lon": 46.9368752}, {"type": "node", "id": 9540146600, "lat": 9.3096793, "lon": 46.9368769}, {"type": "node", "id": 9540146601, "lat": 9.30967, "lon": 46.9368698}, {"type": "node", "id": 9540146602, "lat": 9.3096683, "lon": 46.936858}, {"type": "node", "id": 9540146603, "lat": 9.3096979, "lon": 46.9368658}, {"type": "node", "id": 9547679331, "lat": 9.3535982, "lon": 46.9477134}, {"type": "node", "id": 9547679332, "lat": 9.3536278, "lon": 46.9477832}, {"type": "node", "id": 9547679333, "lat": 9.3535986, "lon": 46.9477959}, {"type": "node", "id": 9547679334, "lat": 9.353569, "lon": 46.9477261}, {"type": "node", "id": 9547679335, "lat": 9.3537014, "lon": 46.9476493}, {"type": "node", "id": 9547679336, "lat": 9.3537113, "lon": 46.9476419}, {"type": "node", "id": 9547679337, "lat": 9.3537236, "lon": 46.9476418}, {"type": "node", "id": 9547679338, "lat": 9.3537336, "lon": 46.9476491}, {"type": "node", "id": 9547679339, "lat": 9.3537338, "lon": 46.9476728}, {"type": "node", "id": 9547679340, "lat": 9.3537239, "lon": 46.9476802}, {"type": "node", "id": 9547679341, "lat": 9.3537116, "lon": 46.9476802}, {"type": "node", "id": 9547679342, "lat": 9.3537016, "lon": 46.947673}, {"type": "node", "id": 9547679343, "lat": 9.3536977, "lon": 46.9476612}, {"type": "node", "id": 9547679344, "lat": 9.3537375, "lon": 46.9476609}, {"type": "node", "id": 9547679345, "lat": 9.3536479, "lon": 46.9477806}, {"type": "node", "id": 9547679346, "lat": 9.3536595, "lon": 46.947777}, {"type": "node", "id": 9547679347, "lat": 9.3536709, "lon": 46.9477809}, {"type": "node", "id": 9547679348, "lat": 9.353678, "lon": 46.9477909}, {"type": "node", "id": 9547679349, "lat": 9.3536706, "lon": 46.947813}, {"type": "node", "id": 9547679350, "lat": 9.353659, "lon": 46.9478167}, {"type": "node", "id": 9547679351, "lat": 9.3536476, "lon": 46.9478128}, {"type": "node", "id": 9547679352, "lat": 9.3536405, "lon": 46.9478028}, {"type": "node", "id": 9547679353, "lat": 9.3536407, "lon": 46.9477905}, {"type": "node", "id": 9547679354, "lat": 9.3536778, "lon": 46.9478032}, {"type": "node", "id": 9547728888, "lat": 9.3556906, "lon": 47.0105483}, {"type": "node", "id": 9547728889, "lat": 9.3556996, "lon": 47.0105421}, {"type": "node", "id": 9547728890, "lat": 9.3557106, "lon": 47.0105424}, {"type": "node", "id": 9547728891, "lat": 9.3557193, "lon": 47.0105492}, {"type": "node", "id": 9547728892, "lat": 9.3557187, "lon": 47.0105703}, {"type": "node", "id": 9547728893, "lat": 9.3557096, "lon": 47.0105765}, {"type": "node", "id": 9547728894, "lat": 9.3556987, "lon": 47.0105762}, {"type": "node", "id": 9547728895, "lat": 9.35569, "lon": 47.0105694}, {"type": "node", "id": 9547728896, "lat": 9.3557224, "lon": 47.0105598}, {"type": "node", "id": 9547728897, "lat": 9.3556869, "lon": 47.0105588}, {"type": "node", "id": 11216905700, "lat": 9.1921717, "lon": 46.8481248}, {"type": "node", "id": 11216905701, "lat": 9.19214, "lon": 46.8481074}, {"type": "node", "id": 11216905702, "lat": 9.1921566, "lon": 46.8480762}, {"type": "node", "id": 11216905703, "lat": 9.1921884, "lon": 46.8480936}, {"type": "node", "id": 11216905704, "lat": 9.1921134, "lon": 46.848077}, {"type": "node", "id": 11216905705, "lat": 9.1920703, "lon": 46.8480636}, {"type": "node", "id": 11216905706, "lat": 9.1920812, "lon": 46.8480279}, {"type": "node", "id": 11216905707, "lat": 9.1921242, "lon": 46.8480413}, {"type": "node", "id": 11216905708, "lat": 9.1920803, "lon": 46.8479281}, {"type": "node", "id": 11216905709, "lat": 9.1920453, "lon": 46.847971}, {"type": "node", "id": 11216905710, "lat": 9.1920236, "lon": 46.8479528}, {"type": "node", "id": 11216905711, "lat": 9.1920587, "lon": 46.8479099}, {"type": "node", "id": 11216905712, "lat": 9.1920127, "lon": 46.8480285}, {"type": "node", "id": 11216905713, "lat": 9.1919591, "lon": 46.8480131}, {"type": "node", "id": 11216905714, "lat": 9.19197, "lon": 46.8479743}, {"type": "node", "id": 11216905715, "lat": 9.1920236, "lon": 46.8479897}, {"type": "node", "id": 11216905716, "lat": 9.1919128, "lon": 46.8482054}, {"type": "node", "id": 11216905717, "lat": 9.1918956, "lon": 46.848241}, {"type": "node", "id": 11216905718, "lat": 9.1919243, "lon": 46.8482552}, {"type": "node", "id": 11216905719, "lat": 9.1919415, "lon": 46.8482197}, {"type": "node", "id": 11216905720, "lat": 9.1918562, "lon": 46.8479662}, {"type": "node", "id": 11216905721, "lat": 9.1918191, "lon": 46.8479669}, {"type": "node", "id": 11216905722, "lat": 9.1918184, "lon": 46.8479273}, {"type": "node", "id": 11216905723, "lat": 9.1918555, "lon": 46.8479267}, {"type": "way", "id": 245422185, "nodes": [2526280017, 2526280018, 2526280019, 2526280020, 2526280017], "tags": {"building": "yes"}}, {"type": "way", "id": 881599429, "nodes": [8198906656, 8198906655, 8198906654, 8198906653, 8198906652, 8198906651, 8198906650, 8198906649, 8198906648, 8198906647, 8198906646, 8198906656], "tags": {"historic": "archaeological_site", "landuse": "cemetery"}}, {"type": "way", "id": 881606821, "nodes": [8198966479, 8198966476, 8198966477, 8198966478, 8198966479], "tags": {"building": "yes"}}, {"type": "way", "id": 881606822, "nodes": [8198966483, 8198966480, 8198966481, 8198966482, 8198966483], "tags": {"building": "yes"}}, {"type": "way", "id": 882013250, "nodes": [8202525872, 8202525871, 8202525870, 8202525869, 8202525872], "tags": {"building": "yes"}}, {"type": "way", "id": 882541743, "nodes": [8207407312, 8207407311, 8207407310, 8207407309, 8207407312], "tags": {"building": "yes"}}, {"type": "way", "id": 882850790, "nodes": [8210321663, 8210321660, 8210321661, 8210321662, 8210321663], "tags": {"building": "yes"}}, {"type": "way", "id": 883295559, "nodes": [8214353957, 8214353954, 8214353955, 8214353956, 8214353957], "tags": {"building": "yes"}}, {"type": "way", "id": 883295560, "nodes": [8214353961, 8214353960, 8214353959, 8214353958, 8214353961], "tags": {"building": "yes"}}, {"type": "way", "id": 903051067, "nodes": [8387503224, 8387503221, 8387503222, 8387503223, 8387503224], "tags": {"building": "yes"}}, {"type": "way", "id": 961544960, "nodes": [8894536886, 8894536885, 8894536884, 8894536883, 8894536882, 8894536887, 8894536881, 8894536880, 8894536879, 8894536878, 8894536886], "tags": {"building": "yes"}}, {"type": "way", "id": 961544961, "nodes": [8894536896, 8894536895, 8894536894, 8894536893, 8894536892, 8894536897, 8894536891, 8894536890, 8894536889, 8894536888, 8894536896], "tags": {"building": "yes"}}, {"type": "way", "id": 961544975, "nodes": [8894537090, 8894537089, 8894537088, 8894537087, 8894537086, 8894537091, 8894537085, 8894537084, 8894537083, 8894537082, 8894537090], "tags": {"building": "yes"}}, {"type": "way", "id": 961594724, "nodes": [8894991452, 8894991451, 8894991450, 8894991449, 8894991448, 8894991453, 8894991447, 8894991446, 8894991445, 8894991444, 8894991452], "tags": {"building": "yes"}}, {"type": "way", "id": 961594725, "nodes": [8894991460, 8894991459, 8894991458, 8894991457, 8894991461, 8894991456, 8894991455, 8894991454, 8894991460], "tags": {"building": "yes"}}, {"type": "way", "id": 961594726, "nodes": [8894991470, 8894991469, 8894991468, 8894991467, 8894991466, 8894991471, 8894991465, 8894991464, 8894991463, 8894991462, 8894991470], "tags": {"building": "yes"}}, {"type": "way", "id": 961594735, "nodes": [8894991628, 8894991627, 8894991626, 8894991625, 8894991624, 8894991629, 8894991623, 8894991622, 8894991621, 8894991620, 8894991628], "tags": {"building": "yes"}}, {"type": "way", "id": 961594736, "nodes": [8894991634, 8894991633, 8894991632, 8894991635, 8894991631, 8894991630, 8894991634], "tags": {"building": "yes"}}, {"type": "way", "id": 961594737, "nodes": [8894991639, 8894991636, 8894991637, 8894991638, 8894991639], "tags": {"building": "yes"}}, {"type": "way", "id": 961594738, "nodes": [8894991647, 8894991646, 8894991645, 8894991644, 8894991648, 8894991643, 8894991642, 8894991641, 8894991647], "tags": {"building": "yes"}}, {"type": "way", "id": 961594739, "nodes": [8894991655, 8894991654, 8894991653, 8894991652, 8894991656, 8894991651, 8894991650, 8894991649, 8894991655], "tags": {"building": "yes"}}, {"type": "way", "id": 961594740, "nodes": [8894991665, 8894991664, 8894991663, 8894991662, 8894991666, 8894991661, 8894991660, 8894991659, 8894991665], "tags": {"building": "yes"}}, {"type": "way", "id": 961594741, "nodes": [8894991675, 8894991674, 8894991673, 8894991672, 8894991671, 8894991676, 8894991670, 8894991669, 8894991668, 8894991667, 8894991675], "tags": {"building": "yes"}}, {"type": "way", "id": 962315737, "nodes": [8901544521, 8901544520, 8901544519, 8901544518, 8901544521], "tags": {"building": "yes"}}, {"type": "way", "id": 962315738, "nodes": [8901544525, 8901544524, 8901544523, 8901544522, 8901544525], "tags": {"building": "yes"}}, {"type": "way", "id": 962315739, "nodes": [8901544529, 8901544528, 8901544527, 8901544526, 8901544529], "tags": {"building": "yes"}}, {"type": "way", "id": 962315747, "nodes": [8901544595, 8901544594, 8901544593, 8901544592, 8901544595], "tags": {"building": "yes"}}, {"type": "way", "id": 962315758, "nodes": [8901544751, 8901544750, 8901544749, 8901544748, 8901544752, 8901544747, 8901544746, 8901544745, 8901544751], "tags": {"building": "yes"}}, {"type": "way", "id": 962315759, "nodes": [8901544759, 8901544758, 8901544757, 8901544756, 8901544760, 8901544755, 8901544754, 8901544753, 8901544759], "tags": {"building": "yes"}}, {"type": "way", "id": 962315760, "nodes": [8901544769, 8901544768, 8901544767, 8901544766, 8901544765, 8901544770, 8901544764, 8901544763, 8901544762, 8901544761, 8901544769], "tags": {"building": "yes"}}, {"type": "way", "id": 962315761, "nodes": [8901544777, 8901544776, 8901544775, 8901544774, 8901544778, 8901544773, 8901544772, 8901544771, 8901544777], "tags": {"building": "yes"}}, {"type": "way", "id": 962315762, "nodes": [8901544787, 8901544786, 8901544785, 8901544784, 8901544783, 8901544788, 8901544782, 8901544781, 8901544780, 8901544779, 8901544787], "tags": {"building": "yes"}}, {"type": "way", "id": 962315765, "nodes": [8901544829, 8901544828, 8901544827, 8901544826, 8901544825, 8901544830, 8901544824, 8901544823, 8901544822, 8901544821, 8901544829], "tags": {"building": "yes"}}, {"type": "way", "id": 962490307, "nodes": [8903274095, 8903274094, 8903274093, 8903274092, 8903274091, 8903274096, 8903274090, 8903274089, 8903274088, 8903274087, 8903274095], "tags": {"building": "yes"}}, {"type": "way", "id": 962556827, "nodes": [8903917685, 8903917684, 8903917683, 8903917682, 8903917681, 8903917686, 8903917680, 8903917679, 8903917678, 8903917677, 8903917685], "tags": {"building": "yes"}}, {"type": "way", "id": 962556831, "nodes": [8903917791, 8903917790, 8903917789, 8903917788, 8903917792, 8903917787, 8903917786, 8903917785, 8903917791], "tags": {"building": "yes"}}, {"type": "way", "id": 962556832, "nodes": [8903917799, 8903917798, 8903917797, 8903917796, 8903917800, 8903917795, 8903917794, 8903917793, 8903917799], "tags": {"building": "yes"}}, {"type": "way", "id": 962556834, "nodes": [8903917819, 8903917818, 8903917817, 8903917816, 8903917815, 8903917820, 8903917814, 8903917813, 8903917812, 8903917811, 8903917819], "tags": {"building": "yes"}}, {"type": "way", "id": 962556835, "nodes": [8903917827, 8903917826, 8903917825, 8903917824, 8903917828, 8903917823, 8903917822, 8903917821, 8903917827], "tags": {"building": "yes"}}, {"type": "way", "id": 962556836, "nodes": [8903917837, 8903917836, 8903917835, 8903917834, 8903917833, 8903917838, 8903917832, 8903917831, 8903917830, 8903917829, 8903917837], "tags": {"building": "yes"}}, {"type": "way", "id": 962556838, "nodes": [8903917854, 8903917853, 8903917852, 8903917851, 8903917850, 8903917855, 8903917849, 8903917848, 8903917847, 8903917846, 8903917854], "tags": {"building": "yes"}}, {"type": "way", "id": 962556839, "nodes": [8903917864, 8903917863, 8903917862, 8903917861, 8903917860, 8903917865, 8903917859, 8903917858, 8903917857, 8903917856, 8903917864], "tags": {"building": "yes"}}, {"type": "way", "id": 962556841, "nodes": [8903917879, 8903917878, 8903917877, 8903917876, 8903917875, 8903917880, 8903917874, 8903917873, 8903917872, 8903917871, 8903917879], "tags": {"building": "yes"}}, {"type": "way", "id": 962626554, "nodes": [8904548577, 8904548576, 8904548575, 8904548574, 8904548573, 8904548578, 8904548572, 8904548571, 8904548570, 8904548569, 8904548577], "tags": {"building": "yes"}}, {"type": "way", "id": 962626555, "nodes": [8904548589, 8904548588, 8904548587, 8904548586, 8904548585, 8904548584, 8904548590, 8904548583, 8904548582, 8904548581, 8904548580, 8904548579, 8904548589], "tags": {"building": "yes"}}, {"type": "way", "id": 962937807, "nodes": [8907426174, 8907426173, 8907426172, 8907426171, 8907426170, 8907426175, 8907426169, 8907426168, 8907426167, 8907426166, 8907426174], "tags": {"building": "yes"}}, {"type": "way", "id": 962937808, "nodes": [8907426184, 8907426183, 8907426182, 8907426181, 8907426180, 8907426185, 8907426179, 8907426178, 8907426177, 8907426176, 8907426184], "tags": {"building": "yes"}}, {"type": "way", "id": 963199890, "nodes": [8909742983, 8909742982, 8909742981, 8909742980, 8909742983], "tags": {"building": "yes"}}, {"type": "way", "id": 963207065, "nodes": [8909795569, 8909795568, 8909795567, 8909795566, 8909795565, 8909795570, 8909795564, 8909795563, 8909795562, 8909795561, 8909795569], "tags": {"building": "yes"}}, {"type": "way", "id": 963207066, "nodes": [8909795579, 8909795578, 8909795577, 8909795576, 8909795575, 8909795580, 8909795574, 8909795573, 8909795572, 8909795571, 8909795579], "tags": {"building": "yes"}}, {"type": "way", "id": 963216925, "nodes": [8909860606, 8909860605, 8909860604, 8909860603, 8909860607, 8909860602, 8909860601, 8909860600, 8909860606], "tags": {"building": "yes"}}, {"type": "way", "id": 963216926, "nodes": [8909860616, 8909860615, 8909860614, 8909860613, 8909860612, 8909871017, 8909860611, 8909860610, 8909860609, 8909860608, 8909860616], "tags": {"building": "yes"}}, {"type": "way", "id": 963253379, "nodes": [8910222022, 8910222021, 8910222020, 8910222019, 8910222023, 8910222018, 8910222017, 8910152716, 8910222022], "tags": {"building": "yes"}}, {"type": "way", "id": 963253380, "nodes": [8910222030, 8910222029, 8910222028, 8910222027, 8910222031, 8910222026, 8910222025, 8910222024, 8910222030], "tags": {"building": "yes"}}, {"type": "way", "id": 963253389, "nodes": [8910222163, 8910222162, 8910222161, 8910222160, 8910222159, 8910222164, 8910222158, 8910222157, 8910222156, 8910222155, 8910222163], "tags": {"building": "yes"}}, {"type": "way", "id": 963253390, "nodes": [8910222175, 8910222174, 8910222173, 8910222172, 8910222171, 8910222170, 8910222176, 8910222169, 8910222168, 8910222167, 8910222166, 8910222165, 8910222175], "tags": {"building": "yes"}}, {"type": "way", "id": 963452648, "nodes": [8911977807, 8911977806, 8911977805, 8911977804, 8911977803, 8911977808, 8911977802, 8911977801, 8911977800, 8911977799, 8911977807], "tags": {"building": "yes"}}, {"type": "way", "id": 963452649, "nodes": [8911997517, 8911977816, 8911977815, 8911977814, 8911977813, 8911997518, 8911977812, 8911977811, 8911977810, 8911977809, 8911997517], "tags": {"building": "yes"}}, {"type": "way", "id": 965617096, "nodes": [8932937505, 8932937502, 8932937503, 8932937504, 8932937505], "tags": {"building": "yes"}}, {"type": "way", "id": 965617097, "nodes": [8932937509, 8932937508, 8932937507, 8932937506, 8932937509], "tags": {"building": "yes"}}, {"type": "way", "id": 965630966, "nodes": [8933105229, 8933105228, 8933105227, 8933105226, 8933105225, 8933105230, 8933105224, 8933105223, 8933105222, 8933105221, 8933105229], "tags": {"building": "yes"}}, {"type": "way", "id": 965630967, "nodes": [8933105239, 8933105238, 8933105237, 8933105236, 8933105235, 8933105240, 8933105234, 8933105233, 8933105232, 8933105231, 8933105239], "tags": {"building": "yes"}}, {"type": "way", "id": 965636724, "nodes": [8933155959, 8933155958, 8933155957, 8933155956, 8933155955, 8933155954, 8933155960, 8933155953, 8933155952, 8933155951, 8933155950, 8933155949, 8933155959], "tags": {"building": "yes"}}, {"type": "way", "id": 965636725, "nodes": [8933155969, 8933155968, 8933155967, 8933155966, 8933155965, 8933155970, 8933155964, 8933155963, 8933155962, 8933155961, 8933155969], "tags": {"building": "yes"}}, {"type": "way", "id": 965653449, "nodes": [8933302085, 8933302084, 8933302083, 8933302082, 8933302081, 8933302086, 8933302080, 8933302079, 8933302078, 8933302077, 8933302085], "tags": {"building": "yes"}}, {"type": "way", "id": 965653450, "nodes": [8933302095, 8933302094, 8933302093, 8933302092, 8933302091, 8933302096, 8933302090, 8933302089, 8933302088, 8933302087, 8933302095], "tags": {"building": "yes"}}, {"type": "way", "id": 1035201502, "nodes": [9535616682, 9535616681, 9535616680, 9535616679, 9535616678, 9535616683, 9535616677, 9535616676, 9535616675, 9535616674, 9535616682], "tags": {"building": "yes"}}, {"type": "way", "id": 1035201503, "nodes": [9535616687, 9535616686, 9535616685, 9535616684, 9535616687], "tags": {"building": "yes"}}, {"type": "way", "id": 1035365026, "nodes": [9537231506, 9537231505, 9537231504, 9537231503, 9537231502, 9537231507, 9537231501, 9537231500, 9537231499, 9537231498, 9537231506], "tags": {"building": "yes"}}, {"type": "way", "id": 1035365027, "nodes": [9537231514, 9537231513, 9537231512, 9537231511, 9537231515, 9537231510, 9537231509, 9537231508, 9537231514], "tags": {"building": "yes"}}, {"type": "way", "id": 1035427472, "nodes": [9537851261, 9537851260, 9537851259, 9537851258, 9537851257, 9537851262, 9537851256, 9537851255, 9537851254, 9537851253, 9537851261], "tags": {"building": "yes"}}, {"type": "way", "id": 1035427473, "nodes": [9537851271, 9537851270, 9537851269, 9537851268, 9537851267, 9537851272, 9537851266, 9537851265, 9537851264, 9537851263, 9537851271], "tags": {"building": "yes"}}, {"type": "way", "id": 1035569647, "nodes": [9540146565, 9540146564, 9540146563, 9540146562, 9540146561, 9540146566, 9540146560, 9540146559, 9540146558, 9540146557, 9540146565], "tags": {"building": "yes"}}, {"type": "way", "id": 1035569648, "nodes": [9540146575, 9540146574, 9540146573, 9540146572, 9540146571, 9540146576, 9540146570, 9540146569, 9540146568, 9540146567, 9540146575], "tags": {"building": "yes"}}, {"type": "way", "id": 1035569650, "nodes": [9540146594, 9540146593, 9540146592, 9540146591, 9540146595, 9540146590, 9540146589, 9540146588, 9540146594], "tags": {"building": "yes"}}, {"type": "way", "id": 1035569651, "nodes": [9540146602, 9540146601, 9540146600, 9540146599, 9540146603, 9540146598, 9540146597, 9540146596, 9540146602], "tags": {"building": "yes"}}, {"type": "way", "id": 1036318092, "nodes": [9547679334, 9547679331, 9547679332, 9547679333, 9547679334], "tags": {"building": "yes"}}, {"type": "way", "id": 1036318093, "nodes": [9547679343, 9547679342, 9547679341, 9547679340, 9547679339, 9547679344, 9547679338, 9547679337, 9547679336, 9547679335, 9547679343], "tags": {"building": "yes"}}, {"type": "way", "id": 1036318094, "nodes": [9547679353, 9547679352, 9547679351, 9547679350, 9547679349, 9547679354, 9547679348, 9547679347, 9547679346, 9547679345, 9547679353], "tags": {"building": "yes"}}, {"type": "way", "id": 1036324077, "nodes": [9547728897, 9547728895, 9547728894, 9547728893, 9547728892, 9547728896, 9547728891, 9547728890, 9547728889, 9547728888, 9547728897], "tags": {"building": "yes"}}, {"type": "way", "id": 1210648663, "nodes": [11216905703, 11216905700, 11216905701, 11216905702, 11216905703], "tags": {"building": "yes"}}, {"type": "way", "id": 1210648664, "nodes": [11216905707, 11216905704, 11216905705, 11216905706, 11216905707], "tags": {"building": "yes"}}, {"type": "way", "id": 1210648665, "nodes": [11216905711, 11216905708, 11216905709, 11216905710, 11216905711], "tags": {"building": "yes"}}, {"type": "way", "id": 1210648666, "nodes": [11216905715, 11216905712, 11216905713, 11216905714, 11216905715], "tags": {"building": "yes"}}, {"type": "way", "id": 1210648667, "nodes": [11216905719, 11216905718, 11216905717, 11216905716, 11216905719], "tags": {"building": "yes"}}, {"type": "way", "id": 1210648668, "nodes": [11216905723, 11216905720, 11216905721, 11216905722, 11216905723], "tags": {"building": "yes"}}]}